clevercx_security_master_types/__init__.py
clevercx_security_master_types/models.py
clevercx_security_master_types/py.typed
clevercx_security_master_types-0.1.18.dist-info/METADATA
clevercx_security_master_types-0.1.18.dist-info/WHEEL
clevercx_security_master_types-0.1.18.dist-info/RECORD
